{
  "updatedAt": "2026-06-26T21:08:38+00:00",
  "items": [
    {
      "name": "Copper",
      "symbol": "CPER",
      "price": 37.34,
      "change": 0.36,
      "changePct": 0.97
    },
    {
      "name": "Silver",
      "symbol": "SLV",
      "price": 53.4,
      "change": 1.04,
      "changePct": 1.99
    },
    {
      "name": "Gold",
      "symbol": "GLD",
      "price": 375.01,
      "change": 5.55,
      "changePct": 1.5
    },
    {
      "name": "Palladium",
      "symbol": "PALL",
      "price": 22.04,
      "change": 0.52,
      "changePct": 2.42
    },
    {
      "name": "Lithium",
      "symbol": "LIT",
      "price": 75.88,
      "change": -2.57,
      "changePct": -3.28
    },
    {
      "name": "Rare Earth",
      "symbol": "REMX",
      "price": 86.64,
      "change": -2.57,
      "changePct": -2.88
    }
  ]
}