{
  "updatedAt": "2026-07-08T20:11:26+00:00",
  "items": [
    {
      "name": "Lithium",
      "price": 18455.17,
      "currency": "EUR",
      "unit": "metric ton",
      "trend": "flat",
      "asOf": "2026-07-07"
    },
    {
      "name": "Copper",
      "price": 13309.0,
      "currency": "USD",
      "unit": "metric ton",
      "trend": "flat",
      "asOf": "2026-07-07"
    },
    {
      "name": "Cobalt",
      "price": 11.19,
      "currency": "EUR",
      "unit": "kilogram",
      "trend": "flat",
      "asOf": "2026-07-07"
    }
  ]
}