{
  "updatedAt": "2026-07-03T21:10:13+00:00",
  "items": [
    {
      "name": "Lithium",
      "price": 18161.37,
      "currency": "EUR",
      "unit": "metric ton",
      "trend": "flat",
      "asOf": "2026-07-02"
    },
    {
      "name": "Copper",
      "price": 13202.0,
      "currency": "USD",
      "unit": "metric ton",
      "trend": "flat",
      "asOf": "2026-07-02"
    },
    {
      "name": "Cobalt",
      "price": 11.24,
      "currency": "EUR",
      "unit": "kilogram",
      "trend": "flat",
      "asOf": "2026-07-02"
    }
  ]
}