[
  {
    "timestamp": "2026-06-10T20:00:00+00:00",
    "nav": 10000,
    "unrealizedPnl": 0,
    "realizedPnl": 0.0,
    "dailyPnl": 0.0,
    "totalPnl": 0
  },
  {
    "timestamp": "2026-06-11T20:00:00+00:00",
    "nav": 10000,
    "unrealizedPnl": 0,
    "realizedPnl": 0.0,
    "dailyPnl": 0,
    "totalPnl": 0
  },
  {
    "timestamp": "2026-06-12T20:00:00+00:00",
    "nav": 10000,
    "unrealizedPnl": 0,
    "realizedPnl": 0.0,
    "dailyPnl": 0,
    "totalPnl": 0
  },
  {
    "timestamp": "2026-06-15T20:00:00+00:00",
    "nav": 10000,
    "unrealizedPnl": 0,
    "realizedPnl": 0.0,
    "dailyPnl": 0,
    "totalPnl": 0
  },
  {
    "timestamp": "2026-06-16T20:00:00+00:00",
    "nav": 10000,
    "unrealizedPnl": 0,
    "realizedPnl": 0.0,
    "dailyPnl": 0,
    "totalPnl": 0
  },
  {
    "timestamp": "2026-06-17T20:00:00+00:00",
    "nav": 10000,
    "unrealizedPnl": 0,
    "realizedPnl": 0.0,
    "dailyPnl": 0,
    "totalPnl": 0
  },
  {
    "timestamp": "2026-06-18T20:00:00+00:00",
    "nav": 10000,
    "unrealizedPnl": 0,
    "realizedPnl": 0.0,
    "dailyPnl": 0,
    "totalPnl": 0
  },
  {
    "timestamp": "2026-06-19T20:00:00+00:00",
    "nav": 10000,
    "unrealizedPnl": 0,
    "realizedPnl": 0.0,
    "dailyPnl": 0,
    "totalPnl": 0
  },
  {
    "timestamp": "2026-06-22T20:00:00+00:00",
    "nav": 9997.25,
    "unrealizedPnl": -2.75,
    "realizedPnl": 0.0,
    "dailyPnl": -2.75,
    "totalPnl": -2.75
  },
  {
    "timestamp": "2026-06-23T20:00:00+00:00",
    "nav": 9576.68,
    "unrealizedPnl": -423.32,
    "realizedPnl": 0.0,
    "dailyPnl": -420.57,
    "totalPnl": -423.32
  },
  {
    "timestamp": "2026-06-24T20:00:00+00:00",
    "nav": 9436.11,
    "unrealizedPnl": -563.89,
    "realizedPnl": 0.0,
    "dailyPnl": -140.57,
    "totalPnl": -563.89
  },
  {
    "timestamp": "2026-06-27T06:08:17+00:00",
    "nav": 9249.71,
    "unrealizedPnl": -750.29,
    "realizedPnl": 0.0,
    "dailyPnl": -186.4,
    "totalPnl": -750.29
  }
]